draw_captcha/__init__.py
draw_captcha/admin.py
draw_captcha/apps.py
draw_captcha/constants.py
draw_captcha/forms.py
draw_captcha/models.py
draw_captcha/urls.py
draw_captcha/utils.py
draw_captcha/views.py
draw_captcha/templates/draw_captcha.html
django_draw_captcha-1.0.5.dist-info/LICENSE
django_draw_captcha-1.0.5.dist-info/METADATA
django_draw_captcha-1.0.5.dist-info/WHEEL
django_draw_captcha-1.0.5.dist-info/top_level.txt
django_draw_captcha-1.0.5.dist-info/RECORD
