Metadata-Version: 2.1
Name: django-draw-captcha
Version: 1.0.5
Summary: Captcha based on drawings by users.
Home-page: https://github.com/henu/django_draw_captcha
Author: Henrik Heino
Author-email: henrik.heino@gmail.com
License: MIT License
Platform: UNKNOWN
